mirsal/__init__.py
mirsal/cli.py
mirsal-0.1.3.dist-info/METADATA
mirsal-0.1.3.dist-info/WHEEL
mirsal-0.1.3.dist-info/entry_points.txt
mirsal-0.1.3.dist-info/top_level.txt
mirsal-0.1.3.dist-info/RECORD
