Metadata-Version: 2.1
Name: mirsal
Version: 0.1.3
Summary: 📄 Live log viewer with Ngrok + Flask
Home-page: https://github.com/bashartalafha/mirsal
Author: Bashar T.
Project-URL: Source Code, https://github.com/bashartalafha/mirsal
Project-URL: Bug Tracker, https://github.com/bashartalafha/mirsal/issues
Classifier: Programming Language :: Python :: 3
Classifier: License :: OSI Approved :: MIT License
Classifier: Operating System :: OS Independent
Requires-Python: >=3.7
Requires-Dist: flask
Requires-Dist: pyngrok
